[{"year":1983,"count":4,"club":"99"},{"year":1983,"count":4,"club":"City"},{"year":1983,"count":2,"club":"Darwin"},{"year":1983,"count":2,"club":"Cantabs"},{"year":1983,"count":2,"club":"Macdonalds"},{"year":1983,"count":1,"club":"Free Press"},{"year":1983,"count":1,"club":"Pye"},{"year":1983,"count":1,"club":"Telephones"},{"year":1983,"count":1,"club":"Rob Roy"},{"year":1984,"count":5,"club":"99"},{"year":1984,"count":4,"club":"City"},{"year":1984,"count":3,"club":"Cantabs"},{"year":1984,"count":3,"club":"Rob Roy"},{"year":1984,"count":2,"club":"Free Press"},{"year":1984,"count":2,"club":"Darwin"},{"year":1984,"count":2,"club":"Macdonalds"},{"year":1984,"count":1,"club":"Addenbrooke's"},{"year":1984,"count":1,"club":"Telephones"},{"year":1985,"count":6,"club":"99"},{"year":1985,"count":6,"club":"City"},{"year":1985,"count":4,"club":"Cantabs"},{"year":1985,"count":2,"club":"Rob Roy"},{"year":1985,"count":2,"club":"Addenbrooke's"},{"year":1985,"count":1,"club":"Darwin"},{"year":1985,"count":1,"club":"Coopers & Lybrand"},{"year":1986,"count":6,"club":"City"},{"year":1986,"count":5,"club":"99"},{"year":1986,"count":4,"club":"Cantabs"},{"year":1986,"count":2,"club":"Addenbrooke's"},{"year":1986,"count":1,"club":"Coopers & Lybrand"},{"year":1986,"count":1,"club":"Univ Sports"},{"year":1986,"count":1,"club":"Lady Somerset"},{"year":1986,"count":1,"club":"Leckhampton"},{"year":1987,"count":5,"club":"City"},{"year":1987,"count":5,"club":"Cantabs"},{"year":1987,"count":4,"club":"99"},{"year":1987,"count":1,"club":"Addenbrooke's"},{"year":1987,"count":1,"club":"Free Press"},{"year":1987,"count":1,"club":"Red Lion Toft"},{"year":1987,"count":1,"club":"Coopers & Lybrand"},{"year":1987,"count":1,"club":"Univ Sports"},{"year":1988,"count":7,"club":"City"},{"year":1988,"count":5,"club":"99"},{"year":1988,"count":5,"club":"Cantabs"},{"year":1988,"count":1,"club":"Free Press"},{"year":1988,"count":1,"club":"Leckhampton"},{"year":1988,"count":1,"club":"Macdonalds"},{"year":1988,"count":1,"club":"Pye"},{"year":1988,"count":1,"club":"Coopers & Lybrand"},{"year":1988,"count":1,"club":"Rob Roy"},{"year":1989,"count":7,"club":"City"},{"year":1989,"count":6,"club":"99"},{"year":1989,"count":4,"club":"Rob Roy"},{"year":1989,"count":3,"club":"Cantabs"},{"year":1989,"count":1,"club":"Free Press"},{"year":1989,"count":1,"club":"Leckhampton"},{"year":1989,"count":1,"club":"Coopers & Lybrand"},{"year":1989,"count":1,"club":"Darwin"},{"year":1989,"count":1,"club":"Macdonalds"},{"year":1989,"count":1,"club":"Pye"},{"year":1990,"count":7,"club":"City"},{"year":1990,"count":4,"club":"99"},{"year":1990,"count":3,"club":"Rob Roy"},{"year":1990,"count":2,"club":"Cantabs"},{"year":1990,"count":2,"club":"Pye"},{"year":1990,"count":1,"club":"Coopers & Lybrand"},{"year":1990,"count":1,"club":"Macdonalds"},{"year":1991,"count":6,"club":"City"},{"year":1991,"count":5,"club":"99"},{"year":1991,"count":4,"club":"Pye"},{"year":1991,"count":2,"club":"Cantabs"},{"year":1991,"count":2,"club":"Rob Roy"},{"year":1991,"count":1,"club":"Barclays Bank"},{"year":1991,"count":1,"club":"Leckhampton"},{"year":1991,"count":1,"club":"Emmanuel"},{"year":1991,"count":1,"club":"Coopers & Lybrand"},{"year":1991,"count":1,"club":"Mott Macdonald"},{"year":1992,"count":6,"club":"99"},{"year":1992,"count":5,"club":"Cantabs"},{"year":1992,"count":4,"club":"City"},{"year":1992,"count":2,"club":"Leckhampton"},{"year":1992,"count":2,"club":"Rob Roy"},{"year":1992,"count":1,"club":"Pye"},{"year":1992,"count":1,"club":"Mott Macdonald"},{"year":1992,"count":1,"club":"Coopers & Lybrand"},{"year":1992,"count":1,"club":"Cam Consultants"},{"year":1992,"count":1,"club":"Maximum Entropy"},{"year":1993,"count":7,"club":"City"},{"year":1993,"count":5,"club":"Cantabs"},{"year":1993,"count":3,"club":"99"},{"year":1993,"count":2,"club":"Leckhampton"},{"year":1993,"count":2,"club":"Rob Roy"},{"year":1993,"count":1,"club":"Mott Macdonald"},{"year":1993,"count":1,"club":"Cam Consultants"},{"year":1993,"count":1,"club":"Lady Somerset"},{"year":1993,"count":1,"club":"Free Press"},{"year":1994,"count":6,"club":"City"},{"year":1994,"count":4,"club":"Rob Roy"},{"year":1994,"count":3,"club":"Free Press"},{"year":1994,"count":2,"club":"Cam Consultants"},{"year":1994,"count":1,"club":"99"},{"year":1994,"count":1,"club":"Pye"},{"year":1994,"count":1,"club":"Red Lion Toft"},{"year":1995,"count":5,"club":"City"},{"year":1995,"count":5,"club":"Free Press"},{"year":1995,"count":4,"club":"Rob Roy"},{"year":1995,"count":4,"club":"Cantabs"},{"year":1995,"count":1,"club":"99"},{"year":1995,"count":1,"club":"Cam Consultants"},{"year":1995,"count":1,"club":"Pye"},{"year":1995,"count":1,"club":"Maximum Entropy"},{"year":1996,"count":6,"club":"City"},{"year":1996,"count":5,"club":"Rob Roy"},{"year":1996,"count":5,"club":"Free Press"},{"year":1996,"count":4,"club":"Cantabs"},{"year":1996,"count":1,"club":"99"},{"year":1996,"count":1,"club":"Cam Consultants"},{"year":1996,"count":1,"club":"Pye"},{"year":1996,"count":1,"club":"Mott MacDonald"},{"year":1996,"count":1,"club":"PA Consultants"},{"year":1997,"count":6,"club":"City"},{"year":1997,"count":5,"club":"Rob Roy"},{"year":1997,"count":5,"club":"Cantabs"},{"year":1997,"count":4,"club":"Free Press"},{"year":1997,"count":2,"club":"99"},{"year":1997,"count":1,"club":"Simoco"},{"year":1997,"count":1,"club":"Mott MacDonald"},{"year":1997,"count":1,"club":"Ionica"},{"year":1998,"count":7,"club":"City"},{"year":1998,"count":5,"club":"Free Press"},{"year":1998,"count":5,"club":"Rob Roy"},{"year":1998,"count":3,"club":"Cantabs"},{"year":1998,"count":2,"club":"99"},{"year":1998,"count":1,"club":"Champs"},{"year":1998,"count":1,"club":"Domino"},{"year":1999,"count":7,"club":"Free Press"},{"year":1999,"count":5,"club":"City"},{"year":1999,"count":4,"club":"Rob Roy"},{"year":1999,"count":3,"club":"99"},{"year":1999,"count":2,"club":"Cantabs"},{"year":1999,"count":1,"club":"Simoco"},{"year":1999,"count":1,"club":"Champs"},{"year":2000,"count":6,"club":"Free Press"},{"year":2000,"count":5,"club":"City"},{"year":2000,"count":5,"club":"Rob Roy"},{"year":2000,"count":4,"club":"Cantabs"},{"year":2000,"count":3,"club":"99"},{"year":2000,"count":3,"club":"Champs"},{"year":2000,"count":1,"club":"Simoco"},{"year":2001,"count":5,"club":"City"},{"year":2001,"count":4,"club":"Rob Roy"},{"year":2001,"count":4,"club":"Camb Blue"},{"year":2001,"count":3,"club":"Cantabs"},{"year":2001,"count":3,"club":"Champs"},{"year":2001,"count":1,"club":"99"},{"year":2001,"count":1,"club":"Simoco"},{"year":2002,"count":4,"club":"Rob Roy"},{"year":2002,"count":4,"club":"X-Press"},{"year":2002,"count":4,"club":"City"},{"year":2002,"count":4,"club":"Champs"},{"year":2002,"count":3,"club":"Cantabs"},{"year":2002,"count":2,"club":"99"},{"year":2002,"count":1,"club":"Simoco"},{"year":2002,"count":1,"club":"St Ives"},{"year":2002,"count":1,"club":"St Radegund"},{"year":2003,"count":6,"club":"Rob Roy"},{"year":2003,"count":4,"club":"City"},{"year":2003,"count":4,"club":"99"},{"year":2003,"count":4,"club":"Champs"},{"year":2003,"count":3,"club":"X-Press"},{"year":2003,"count":3,"club":"Cantabs"},{"year":2003,"count":1,"club":"Simoco"},{"year":2003,"count":1,"club":"St Ives"},{"year":2003,"count":1,"club":"St Radegund"},{"year":2004,"count":6,"club":"Champs"},{"year":2004,"count":5,"club":"99"},{"year":2004,"count":4,"club":"Rob Roy"},{"year":2004,"count":4,"club":"City"},{"year":2004,"count":4,"club":"Cantabs"},{"year":2004,"count":3,"club":"X-Press"},{"year":2004,"count":2,"club":"Simoco"},{"year":2004,"count":1,"club":"St Ives"},{"year":2004,"count":1,"club":"St Radegund"},{"year":2005,"count":5,"club":"City"},{"year":2005,"count":5,"club":"Champs"},{"year":2005,"count":4,"club":"Rob Roy"},{"year":2005,"count":4,"club":"Cantabs"},{"year":2005,"count":3,"club":"99"},{"year":2005,"count":2,"club":"X-Press"},{"year":2005,"count":2,"club":"Simoco"},{"year":2005,"count":1,"club":"St Ives"},{"year":2005,"count":1,"club":"St Radegund"},{"year":2005,"count":1,"club":"Max Entropy"},{"year":2005,"count":1,"club":"Isle of Ely"},{"year":2006,"count":7,"club":"City"},{"year":2006,"count":6,"club":"Champs"},{"year":2006,"count":5,"club":"99"},{"year":2006,"count":4,"club":"Cantabs"},{"year":2006,"count":3,"club":"Simoco"},{"year":2006,"count":2,"club":"X-Press"},{"year":2006,"count":2,"club":"St Radegund"},{"year":2006,"count":1,"club":"Rob Roy"},{"year":2006,"count":1,"club":"Camb Veterans"},{"year":2006,"count":1,"club":"Max Entropy"},{"year":2006,"count":1,"club":"St Ives"},{"year":2006,"count":1,"club":"Isle of Ely"},{"year":2007,"count":8,"club":"City"},{"year":2007,"count":8,"club":"Champs"},{"year":2007,"count":3,"club":"99"},{"year":2007,"count":3,"club":"Cantabs"},{"year":2007,"count":3,"club":"X-Press"},{"year":2007,"count":2,"club":"Rob Roy"},{"year":2007,"count":2,"club":"Simoco"},{"year":2007,"count":2,"club":"St Radegund"},{"year":2007,"count":1,"club":"Camb Veterans"},{"year":2007,"count":1,"club":"Max Entropy"},{"year":2007,"count":1,"club":"St Ives/Ely"},{"year":2008,"count":9,"club":"City"},{"year":2008,"count":8,"club":"Champs"},{"year":2008,"count":4,"club":"99"},{"year":2008,"count":4,"club":"Cantabs"},{"year":2008,"count":3,"club":"X-Press"},{"year":2008,"count":2,"club":"Rob Roy"},{"year":2008,"count":2,"club":"Chesterton"},{"year":2008,"count":1,"club":"Camb Veterans"},{"year":2008,"count":1,"club":"St Radegund"},{"year":2009,"count":10,"club":"Champs"},{"year":2009,"count":8,"club":"City"},{"year":2009,"count":4,"club":"99"},{"year":2009,"count":4,"club":"Cantabs"},{"year":2009,"count":3,"club":"Rob Roy"},{"year":2009,"count":3,"club":"X-Press"},{"year":2009,"count":2,"club":"Chesterton"},{"year":2009,"count":1,"club":"Camb Veterans"},{"year":2009,"count":1,"club":"St Radegund"},{"year":2010,"count":8,"club":"City"},{"year":2010,"count":8,"club":"Champs"},{"year":2010,"count":6,"club":"Cantabs"},{"year":2010,"count":4,"club":"99"},{"year":2010,"count":2,"club":"Chesterton"},{"year":2010,"count":2,"club":"X-Press"},{"year":2010,"count":2,"club":"St Radegund"},{"year":2010,"count":1,"club":"Camb Veterans"},{"year":2010,"count":1,"club":"Rob Roy"},{"year":2010,"count":1,"club":"St Neots"},{"year":2010,"count":1,"club":"Max Entropy"},{"year":2011,"count":9,"club":"City"},{"year":2011,"count":8,"club":"Champs"},{"year":2011,"count":5,"club":"Cantabs"},{"year":2011,"count":4,"club":"99"},{"year":2011,"count":2,"club":"St Neots"},{"year":2011,"count":2,"club":"Chesterton"},{"year":2011,"count":2,"club":"X-Press"},{"year":2011,"count":2,"club":"St Radegund"},{"year":2011,"count":1,"club":"Camb Veterans"},{"year":2011,"count":1,"club":"Isle of Ely"},{"year":2012,"count":8,"club":"City"},{"year":2012,"count":7,"club":"Champs"},{"year":2012,"count":6,"club":"Cantabs"},{"year":2012,"count":4,"club":"99"},{"year":2012,"count":2,"club":"St Neots"},{"year":2012,"count":2,"club":"X-Press"},{"year":2012,"count":2,"club":"Chesterton"},{"year":2012,"count":2,"club":"St Radegund"},{"year":2012,"count":1,"club":"Camb Veterans"},{"year":2012,"count":1,"club":"Rob Roy"},{"year":2012,"count":1,"club":"Isle of Ely"},{"year":2013,"count":11,"club":"City"},{"year":2013,"count":8,"club":"Champs"},{"year":2013,"count":7,"club":"Cantabs"},{"year":2013,"count":5,"club":"99"},{"year":2013,"count":2,"club":"X-Press"},{"year":2013,"count":2,"club":"Chesterton"},{"year":2013,"count":2,"club":"St Radegund"},{"year":2013,"count":1,"club":"Camb Veterans"},{"year":2013,"count":1,"club":"Rob Roy"},{"year":2013,"count":1,"club":"St Neots"},{"year":2013,"count":1,"club":"Isle of Ely"},{"year":2014,"count":8,"club":"City"},{"year":2014,"count":8,"club":"99"},{"year":2014,"count":7,"club":"Cantabs"},{"year":2014,"count":7,"club":"Champs"},{"year":2014,"count":3,"club":"Rob Roy"},{"year":2014,"count":3,"club":"X-Press"},{"year":2014,"count":3,"club":"Chesterton"},{"year":2014,"count":2,"club":"St Neots"},{"year":2014,"count":2,"club":"St Radegund"},{"year":2014,"count":1,"club":"Camb Veterans"},{"year":2014,"count":1,"club":"Isle of Ely"},{"year":2015,"count":10,"club":"City"},{"year":2015,"count":10,"club":"Cantabs"},{"year":2015,"count":7,"club":"99"},{"year":2015,"count":6,"club":"Champs"},{"year":2015,"count":4,"club":"Rob Roy"},{"year":2015,"count":3,"club":"X-Press"},{"year":2015,"count":3,"club":"Chesterton"},{"year":2015,"count":2,"club":"St Neots"},{"year":2015,"count":2,"club":"St Radegund"},{"year":2015,"count":1,"club":"Camb Veterans"},{"year":2015,"count":1,"club":"Isle of Ely"},{"year":2016,"count":11,"club":"Cantabs"},{"year":2016,"count":8,"club":"City"},{"year":2016,"count":7,"club":"Champs"},{"year":2016,"count":6,"club":"99"},{"year":2016,"count":4,"club":"Rob Roy"},{"year":2016,"count":4,"club":"X-Press"},{"year":2016,"count":3,"club":"Chesterton"},{"year":2016,"count":2,"club":"St Neots"},{"year":2016,"count":2,"club":"St Radegund"},{"year":2016,"count":1,"club":"Camb Veterans"},{"year":2016,"count":1,"club":"Isle of Ely"},{"year":2017,"count":12,"club":"Cantabs"},{"year":2017,"count":8,"club":"City"},{"year":2017,"count":7,"club":"99"},{"year":2017,"count":6,"club":"Champs"},{"year":2017,"count":3,"club":"X-Press"},{"year":2017,"count":3,"club":"Rob Roy"},{"year":2017,"count":3,"club":"Chesterton"},{"year":2017,"count":2,"club":"St Neots"},{"year":2017,"count":2,"club":"Isle of Ely"},{"year":2017,"count":1,"club":"Camb Veterans"},{"year":2017,"count":1,"club":"St Radegund"},{"year":2018,"count":11,"club":"Cantabs"},{"year":2018,"count":8,"club":"City"},{"year":2018,"count":7,"club":"99"},{"year":2018,"count":6,"club":"Champs"},{"year":2018,"count":4,"club":"X-Press"},{"year":2018,"count":3,"club":"Chesterton"},{"year":2018,"count":2,"club":"St Neots"},{"year":2018,"count":2,"club":"Rob Roy"},{"year":2018,"count":2,"club":"Isle of Ely"},{"year":2018,"count":1,"club":"St Radegund"},{"year":2019,"count":10,"club":"Cantabs"},{"year":2019,"count":9,"club":"99"},{"year":2019,"count":8,"club":"City"},{"year":2019,"count":7,"club":"Champs"},{"year":2019,"count":4,"club":"Chesterton"},{"year":2019,"count":3,"club":"X-Press"},{"year":2019,"count":2,"club":"Isle of Ely"},{"year":2019,"count":1,"club":"Rob Roy"},{"year":2021,"count":12,"club":"Cantabs"},{"year":2021,"count":9,"club":"City"},{"year":2021,"count":6,"club":"99"},{"year":2021,"count":4,"club":"Champs"},{"year":2021,"count":3,"club":"X-Press"},{"year":2021,"count":3,"club":"Chesterton"},{"year":2021,"count":2,"club":"St Neots"},{"year":2021,"count":2,"club":"Rob Roy"},{"year":2021,"count":2,"club":"Isle of Ely"},{"year":2022,"count":14,"club":"Cantabs"},{"year":2022,"count":12,"club":"City"},{"year":2022,"count":7,"club":"99"},{"year":2022,"count":5,"club":"X-Press"},{"year":2022,"count":4,"club":"Champs"},{"year":2022,"count":3,"club":"Chesterton"},{"year":2022,"count":3,"club":"St Neots"},{"year":2022,"count":2,"club":"Rob Roy"},{"year":2022,"count":2,"club":"Isle of Ely"},{"year":2023,"count":13,"club":"Cantabs"},{"year":2023,"count":9,"club":"City"},{"year":2023,"count":6,"club":"99"},{"year":2023,"count":4,"club":"Champs"},{"year":2023,"count":3,"club":"X-Press"},{"year":2023,"count":3,"club":"Chesterton"},{"year":2023,"count":3,"club":"Rob Roy"},{"year":2023,"count":2,"club":"Isle of Ely"},{"year":2023,"count":2,"club":"St Radegund"},{"year":2023,"count":1,"club":"St Neots"},{"year":2023,"count":1,"club":"Camb Vets"}]